hil/uds/server/__init__.py
hil/uds/server/__main__.py
hil/uds/server/gp_bin.py
hil/uds/server/gp_server.py
hil/uds/server/models.py
hil/uds/server/servers.py
hil_uds_server-0.0.4.dist-info/AUTHORS
hil_uds_server-0.0.4.dist-info/METADATA
hil_uds_server-0.0.4.dist-info/WHEEL
hil_uds_server-0.0.4.dist-info/entry_points.txt
hil_uds_server-0.0.4.dist-info/pbr.json
hil_uds_server-0.0.4.dist-info/top_level.txt
hil_uds_server-0.0.4.dist-info/RECORD
