Metadata-Version: 2.1
Name: hil-uds-server
Version: 0.0.4
Summary: configurable UDS server for Carota HIL
Author: notmmao
Author-email: notmmao@gmail.com
License: Carota HIL License
Classifier: Programming Language :: Python :: 3
Classifier: Operating System :: OS Independent
License-File: AUTHORS
Requires-Dist: hil-core
Requires-Dist: pyyaml
Requires-Dist: pydantic
Requires-Dist: pydantic-yaml
Requires-Dist: watchdog
Requires-Dist: fastapi
Requires-Dist: uvicorn
Requires-Dist: requests
